clever_sync/__init__.py
clever_sync/enrollments.py
clever_sync/sections.py
clever_sync/sftp_sync.py
clever_sync/students.py
clever_sync/teachers.py
clever_sync-0.1.4.dist-info/WHEEL
clever_sync-0.1.4.dist-info/entry_points.txt
clever_sync-0.1.4.dist-info/METADATA
clever_sync-0.1.4.dist-info/RECORD
