Metadata-Version: 2.3
Name: clever-sync
Version: 0.1.4
Summary: Add your description here
Author: jvansant13
Author-email: jvansant13 <jermey.vansant@davinciacademy.org>
Requires-Dist: oneroster-api>=0.1.2
Requires-Dist: paramiko>=4.0.0
Requires-Python: >=3.12
